qbench/__init__.py
qbench/api.py
qbench/auth.py
qbench/endpoints.py
qbench/exceptions.py
qbench/py.typed
qbench-1.0.2.dist-info/licenses/LICENSE
qbench-1.0.2.dist-info/METADATA
qbench-1.0.2.dist-info/WHEEL
qbench-1.0.2.dist-info/top_level.txt
qbench-1.0.2.dist-info/RECORD
