Metadata-Version: 2.4
Name: qbench
Version: 1.0.2
Summary: Python SDK for QBench LIMS API
Home-page: https://github.com/nwilliams-cts/qbench
Author: Smithers
Author-email: Smithers <nwilliams@smithers.com>
License-Expression: MIT
Project-URL: PYPI, https://pypi.org/project/qbench
Project-URL: Documentation, https://junctionconcepts.zendesk.com/hc/en-us/articles/360030760992-QBench-REST-API-v1-0-Documentation-Full
Project-URL: Repository, https://github.com/nwilliams-cts/qbench.git
Project-URL: Issues, https://github.com/nwilliams-cts/qbench/issues
Classifier: Development Status :: 3 - Alpha
Classifier: Intended Audience :: Developers
Classifier: Operating System :: OS Independent
Classifier: Programming Language :: Python :: 3
Classifier: Programming Language :: Python :: 3.8
Classifier: Programming Language :: Python :: 3.9
Classifier: Programming Language :: Python :: 3.10
Classifier: Programming Language :: Python :: 3.11
Classifier: Programming Language :: Python :: 3.12
Classifier: Programming Language :: Python :: 3.13
Classifier: Topic :: Scientific/Engineering
Classifier: Topic :: Software Development :: Libraries :: Python Modules
Requires-Python: >=3.8
License-File: LICENSE
Requires-Dist: requests>=2.32.4
Requires-Dist: aiohttp>=3.12.14
Requires-Dist: PyJWT>=2.10.1
Requires-Dist: tenacity>=8.0.0
Requires-Dist: typing-extensions>=4.0.0; python_version < "3.10"
Provides-Extra: dev
Requires-Dist: pytest>=7.0.0; extra == "dev"
Requires-Dist: pytest-asyncio>=0.21.0; extra == "dev"
Requires-Dist: pytest-cov>=4.0.0; extra == "dev"
Requires-Dist: black>=25.1.0; extra == "dev"
Requires-Dist: flake8>=4.0.0; extra == "dev"
Requires-Dist: mypy>=0.950; extra == "dev"
Requires-Dist: pre-commit>=2.0.0; extra == "dev"
Requires-Dist: responses>=0.22.0; extra == "dev"
Requires-Dist: aioresponses>=0.7.0; extra == "dev"
Dynamic: author
Dynamic: home-page
Dynamic: license-file
Dynamic: requires-python
